mac_cleaner/__init__.py
mac_cleaner/cleaner.py
mac_cleaner/i18n.py
mac_cleaner/locales/mac_cleaner.pot
mac_cleaner/locales/en_US/LC_MESSAGES/mac_cleaner.mo
mac_cleaner/locales/en_US/LC_MESSAGES/mac_cleaner.po
mac_cleaner/locales/es_ES/LC_MESSAGES/mac_cleaner.mo
mac_cleaner/locales/es_ES/LC_MESSAGES/mac_cleaner.po
mac_cleaner-1.1.0.dist-info/licenses/LICENSE
mac_cleaner-1.1.0.dist-info/METADATA
mac_cleaner-1.1.0.dist-info/WHEEL
mac_cleaner-1.1.0.dist-info/entry_points.txt
mac_cleaner-1.1.0.dist-info/top_level.txt
mac_cleaner-1.1.0.dist-info/RECORD
