Metadata-Version: 2.4
Name: mac-cleaner
Version: 1.1.0
Summary: A safe and intelligent disk cleaning utility for macOS
Author-email: Noel Moreno Lemus <nmlemus@gmail.com>
License: MIT
Project-URL: Homepage, https://github.com/nmlemus/mac-cleaner
Project-URL: Bug Reports, https://github.com/nmlemus/mac-cleaner/issues
Project-URL: Source, https://github.com/nmlemus/mac-cleaner
Project-URL: Buy Me a Coffee, https://www.buymeacoffee.com/nmlemus
Keywords: macos,cleaner,disk-space,cleanup,cache,temporary-files
Classifier: Development Status :: 4 - Beta
Classifier: Environment :: Console
Classifier: Intended Audience :: End Users/Desktop
Classifier: License :: OSI Approved :: MIT License
Classifier: Operating System :: MacOS
Classifier: Programming Language :: Python :: 3
Classifier: Programming Language :: Python :: 3.8
Classifier: Programming Language :: Python :: 3.9
Classifier: Programming Language :: Python :: 3.10
Classifier: Programming Language :: Python :: 3.11
Classifier: Programming Language :: Python :: 3.12
Classifier: Topic :: System :: Systems Administration
Classifier: Topic :: Utilities
Requires-Python: >=3.8
License-File: LICENSE
Provides-Extra: dev
Requires-Dist: pytest>=7.0; extra == "dev"
Requires-Dist: pytest-cov>=4.0; extra == "dev"
Requires-Dist: black>=23.0; extra == "dev"
Requires-Dist: flake8>=6.0; extra == "dev"
Requires-Dist: mypy>=1.0; extra == "dev"
Dynamic: license-file
